bastionlab/__init__.py
bastionlab/client.py
bastionlab/errors.py
bastionlab/keys.py
bastionlab/version.py
bastionlab/pb/__init__.py
bastionlab/pb/bastionlab_pb2.py
bastionlab/pb/bastionlab_pb2_grpc.py
bastionlab/pb/bastionlab_polars_pb2.py
bastionlab/pb/bastionlab_polars_pb2_grpc.py
bastionlab/pb/bastionlab_torch_pb2.py
bastionlab/pb/bastionlab_torch_pb2_grpc.py
bastionlab/polars/__init__.py
bastionlab/polars/client.py
bastionlab/polars/policy.py
bastionlab/polars/remote_polars.py
bastionlab/polars/utils.py
bastionlab/torch/__init__.py
bastionlab/torch/client.py
bastionlab/torch/learner.py
bastionlab/torch/optimizer_config.py
bastionlab/torch/utils.py
bastionlab/torch/psg/__init__.py
bastionlab/torch/psg/convert.py
bastionlab/torch/psg/nn.py
bastionlab-0.3.7.dist-info/METADATA
bastionlab-0.3.7.dist-info/WHEEL
bastionlab-0.3.7.dist-info/top_level.txt
bastionlab-0.3.7.dist-info/RECORD
