Metadata-Version: 2.1
Name: bastionlab
Version: 0.3.7
Summary: Client for BastionLab Confidential Analytics.
Author: Kwabena Amponsem, Lucas Bourtoule
Author-email: kwabena.amponsem@mithrilsecurity.io, luacs.bourtoule@nithrilsecurity.io
Keywords: confidential computing training client enclave amd-sev machine learning
Classifier: Programming Language :: Python :: 3
Requires-Dist: polars (==0.14.24)
Requires-Dist: torch (==1.13.1)
Requires-Dist: typing-extensions (~=4.4)
Requires-Dist: grpcio (==1.47.0)
Requires-Dist: grpcio-tools (==1.47.0)
Requires-Dist: colorama (~=0.4.6)
Requires-Dist: cryptography (~=38.0)
Requires-Dist: seaborn (~=0.12.0)
Requires-Dist: pyarrow (~=10.0)
Requires-Dist: protobuf (==3.20.2)
Requires-Dist: six (~=1.16.0)
Requires-Dist: numpy (~=1.21)
Requires-Dist: tqdm (~=4.64)
